website_tool/.~lock.example.org.csv#
website_tool/.~lock.we-inform.de.csv#
website_tool/.~lock.we-inform.de.error.csv#
website_tool/.~lock.wg-ing.de.csv#
website_tool/__init__.py
website_tool/__main__.py
website_tool/check.py
website_tool/extract_links.py
website_tool-0.0.11.dist-info/LICENSE
website_tool-0.0.11.dist-info/METADATA
website_tool-0.0.11.dist-info/WHEEL
website_tool-0.0.11.dist-info/RECORD
