Metadata-Version: 2.1
Name: website-tool
Version: 0.0.11
Summary: A tool to make it simpler to maintain a website against the increasing entropy on the web.
License: AGPL-3.0-or-later
Author: CSDUMMI
Author-email: CSDUMMI.MISQUALITY@SIMPLELOGIN.CO
Requires-Python: >=3.8,<4.0
Classifier: License :: OSI Approved :: GNU Affero General Public License v3 or later (AGPLv3+)
Classifier: Programming Language :: Python :: 3
Classifier: Programming Language :: Python :: 3.8
Classifier: Programming Language :: Python :: 3.9
Classifier: Programming Language :: Python :: 3.10
Classifier: Programming Language :: Python :: 3.11
Requires-Dist: aiohttp (>=3.8.4,<4.0.0)
Requires-Dist: pyvis (>=0.3.2,<0.4.0)
Requires-Dist: pyyaml (>=6.0,<7.0)
Requires-Dist: requests (>=2.28.2,<3.0.0)
Requires-Dist: tqdm (>=4.65.0,<5.0.0)
